t_helpers/__init__.py
t_helpers/config.py
t_helpers/flights.py
t_helpers/mailing.py
t_helpers/manga.py
t_helpers/push_bullet.py
t_helpers/sptrans.py
t_helpers/telegram.py
t_helpers/youtube.py
t_helpers-0.2.1.data/scripts/tcli
t_helpers-0.2.1.dist-info/DESCRIPTION.rst
t_helpers-0.2.1.dist-info/METADATA
t_helpers-0.2.1.dist-info/RECORD
t_helpers-0.2.1.dist-info/WHEEL
t_helpers-0.2.1.dist-info/metadata.json
t_helpers-0.2.1.dist-info/top_level.txt
