Metadata-Version: 2.0
Name: t-helpers
Version: 0.2.1
Summary: Tafarel personal helper tools
Home-page: https://github.com/ArrowsX/t-helpers
Author: Tafarel Yan
Author-email: tafarel.yan@gmail.com
License: UNKNOWN
Platform: UNKNOWN
Requires-Dist: beautifulsoup4
Requires-Dist: requests
Requires-Dist: selenium
Requires-Dist: youtube-dl
